transvec/__init__.py
transvec/tokenizers.py
transvec/transformers.py
transvec-0.1.0.dist-info/LICENSE
transvec-0.1.0.dist-info/METADATA
transvec-0.1.0.dist-info/WHEEL
transvec-0.1.0.dist-info/top_level.txt
transvec-0.1.0.dist-info/RECORD
