Metadata-Version: 2.1
Name: transvec
Version: 0.1.0
Summary: Multilingual word embeddings.
Home-page: http://github.com/big-o/transvec
Author: big-o
Author-email: big-o@users.noreply.github.com
License: GNU GPLv3
Keywords: Translation,Machine Translation,Bilingual,Multilingual,Singular Value Decomposition,SVD,Latent Semantic Indexing,LSA,LSI,Latent Dirichlet Allocation,LDA,Hierarchical Dirichlet Process,HDP,Random Projections,TFIDF,word2vec,doc2vec
Platform: UNKNOWN
Classifier: Development Status :: 3 - Alpha
Classifier: Environment :: Console
Classifier: Intended Audience :: Science/Research
Classifier: License :: OSI Approved :: GNU General Public License v3 (GPLv3)
Classifier: Operating System :: OS Independent
Classifier: Programming Language :: Python :: 3.7
Classifier: Programming Language :: Python :: 3.8
Classifier: Topic :: Scientific/Engineering :: Artificial Intelligence
Classifier: Topic :: Scientific/Engineering :: Information Analysis
Classifier: Topic :: Text Processing :: Linguistic
Requires-Python: >=3.7
Requires-Dist: nltk (>=3.5)
Requires-Dist: numpy
Requires-Dist: scikit-learn
Provides-Extra: dev
Provides-Extra: test
